tml/__init__.py
tree_markup_language-0.0.1.dist-info/LICENSE
tree_markup_language-0.0.1.dist-info/METADATA
tree_markup_language-0.0.1.dist-info/WHEEL
tree_markup_language-0.0.1.dist-info/entry_points.txt
tree_markup_language-0.0.1.dist-info/top_level.txt
tree_markup_language-0.0.1.dist-info/RECORD
