Metadata-Version: 2.1
Name: tree-markup-language
Version: 0.0.1
Summary: Tree markup language
Author-email: Valerio Iacobucci <valerio@valerioiacobucci.com>
Project-URL: Homepage, https://github.com/iacobucci/tree-markup-language
Classifier: Programming Language :: Python :: 3
Classifier: License :: OSI Approved :: MIT License
Classifier: Operating System :: OS Independent
Requires-Python: >=3.7
License-File: LICENSE
